Design_files/arctan_lookup.v
////////////////////////////////////////////////////////////////////////////////
// Author: Sudeep Joshi
// Date: 24/08/2023
// Description: Arctan Look-Up table for CORDIC Unit ( Q3.29 representation is chosen)
////////////////////////////////////////////////////////////////////////////////

module arctan_lookup #(parameter N = 32)
(
input [4:0] j,
output [N-1:0] arctan
);

reg [N-1:0] lookup_table[0:31];

initial
begin
	lookup_table[0]  <= 32'b000_11001001000011111101101010100;
	lookup_table[1]  <= 32'b000_01110110101100011001110000010;
	lookup_table[2]  <= 32'b000_00111110101101101110101111110;
	lookup_table[3]  <= 32'b000_00011111110101011011101010011;
	lookup_table[4]  <= 32'b000_00001111111110101010110111011;
	lookup_table[5]  <= 32'b000_00000111111111110101010101101;
	lookup_table[6]  <= 32'b000_00000011111111111110101010101;
	lookup_table[7]  <= 32'b000_00000001111111111111110101010;
	lookup_table[8]  <= 32'b000_00000000111111111111111110101;
	lookup_table[9]  <= 32'b000_00000000011111111111111111110;
	lookup_table[10] <= 32'b000_00000000001111111111111111111;
	lookup_table[11] <= 32'b000_00000000000111111111111111111;
	lookup_table[12] <= 32'b000_00000000000011111111111111111;
	lookup_table[13] <= 32'b000_00000000000000111111111111111;
	lookup_table[14] <= 32'b000_00000000000000011111111111111;
	lookup_table[15] <= 32'b000_00000000000000001111111111111;
	lookup_table[16] <= 32'b000_00000000000000000111111111111;
	lookup_table[17] <= 32'b000_00000000000000000011111111111;
	lookup_table[18] <= 32'b000_00000000000000000001111111111;
	lookup_table[19] <= 32'b000_00000000000000000000111111111;
	lookup_table[20] <= 32'b000_00000000000000000000011111111;
	lookup_table[21] <= 32'b000_00000000000000000000001111111;
	lookup_table[22] <= 32'b000_00000000000000000000000111111;
	lookup_table[23] <= 32'b000_00000000000000000000000011111;
	lookup_table[24] <= 32'b000_00000000000000000000000001111;
	lookup_table[25] <= 32'b000_00000000000000000000000000111;
	lookup_table[26] <= 32'b000_00000000000000000000000000011;
	lookup_table[27] <= 32'b000_00000000000000000000000000001;
	lookup_table[28] <= 32'b000_00000000000000000000000000000;
end

assign arctan = lookup_table[j];

endmodule

rtl/tb_arctan_lookup.v
////////////////////////////////////////////////////////////////////////////////
// Author: Sudeep Joshi
// Date: 24/08/2023
// Description: Test bench for Arctan Look-Up table for CORDIC Unit ( Q3.29 representation is chosen)
////////////////////////////////////////////////////////////////////////////////

module test_arctan_lookup;

reg [4:0] j;
wire [31:0] arctan;

arctan_lookup #(32) dut (
    .j(j),
    .arctan(arctan)
);

initial begin
    $dumpfile("waveform.vcd");
    $dumpvars(0, dut);

    for (j = 0; j <= 28; j = j + 1) begin
        #5;
        $display("j = %d, arctan = %b", j, arctan);
    end
    $finish;
end

endmodule

Design_files/waveform.vcd
$date
	Fri Aug 25 00:15:50 2023
$end
$version
	Icarus Verilog
$end
$timescale
	1s
$end
$scope module test_arctan_lookup $end
$scope module dut $end
$var wire 32 ! arctan [31:0] $end
$var wire 5 " j [4:0] $end
$upscope $end
$upscope $end
$enddefinitions $end
#0
$dumpvars
b0 "
b11001001000011111101101010100 !
$end
#5
b1110110101100011001110000010 !
b1 "
#10
b111110101101101110101111110 !
b10 "
#15
b11111110101011011101010011 !
b11 "
#20
b1111111110101010110111011 !
b100 "
#25
b111111111110101010101101 !
b101 "
#30
b11111111111110101010101 !
b110 "
#35
b1111111111111110101010 !
b111 "
#40
b111111111111111110101 !
b1000 "
#45
b11111111111111111110 !
b1001 "
#50
b1111111111111111111 !
b1010 "
#55
b111111111111111111 !
b1011 "
#60
b11111111111111111 !
b1100 "
#65
b111111111111111 !
b1101 "
#70
b11111111111111 !
b1110 "
#75
b1111111111111 !
b1111 "
#80
b111111111111 !
b10000 "
#85
b11111111111 !
b10001 "
#90
b1111111111 !
b10010 "
#95
b111111111 !
b10011 "
#100
b11111111 !
b10100 "
#105
b1111111 !
b10101 "
#110
b111111 !
b10110 "
#115
b11111 !
b10111 "
#120
b1111 !
b11000 "
#125
b111 !
b11001 "
#130
b11 !
b11010 "
#135
b1 !
b11011 "
#140
b0 !
b11100 "
#145
bx !
b11101 "
